activity_detection/__init__.py
activity_detection/evaluation.py
activity_detection/utils.py
activity_detection_evaluation-0.2.1.dist-info/METADATA
activity_detection_evaluation-0.2.1.dist-info/WHEEL
activity_detection_evaluation-0.2.1.dist-info/top_level.txt
activity_detection_evaluation-0.2.1.dist-info/RECORD
