Metadata-Version: 2.1
Name: activity-detection-evaluation
Version: 0.2.1
Summary: Library for evaluating activity detection
Author: Javier Smith
License: MIT
Requires-Dist: matplotlib (==3.6.2)
Requires-Dist: pandas (==1.5.1)
Requires-Dist: librosa (==0.9.2)
